protec/__init__.py
protec/py.typed
protec-0.0.0.dist-info/LICENSE
protec-0.0.0.dist-info/WHEEL
protec-0.0.0.dist-info/entry_points.txt
protec-0.0.0.dist-info/METADATA
protec-0.0.0.dist-info/RECORD
