Metadata-Version: 2.1
Name: protec
Version: 0.0.0
Summary: Protec
Home-page: https://github.com/mike0sv/protec
License: Apache-2.0
Author: Mike Sveshnikov
Author-email: mike0sv@gmail.com
Requires-Python: >=3.7,<4.0
Classifier: Development Status :: 1 - Planning
Classifier: License :: OSI Approved :: Apache Software License
Classifier: Programming Language :: Python :: 3
Classifier: Programming Language :: Python :: 3.7
Classifier: Programming Language :: Python :: 3.8
Classifier: Programming Language :: Python :: 3.9
Classifier: Programming Language :: Python :: 3.10
Classifier: Programming Language :: Python :: 3.11
Requires-Dist: click (>=8.0.1)
Project-URL: Changelog, https://github.com/mike0sv/protec/releases
Project-URL: Documentation, https://protec.readthedocs.io
Project-URL: Repository, https://github.com/mike0sv/protec
